shellog/__init__.py
shellog-1.0.5.dist-info/licenses/LICENSE
shellog-1.0.5.dist-info/METADATA
shellog-1.0.5.dist-info/WHEEL
shellog-1.0.5.dist-info/top_level.txt
shellog-1.0.5.dist-info/RECORD
